asynccpu/__init__.py
asynccpu/process_task.py
asynccpu/process_task_pool_executor.py
asynccpu/process_terminator.py
asynccpu/py.typed
asynccpu/subprocess.py
asynccpu/types.py
asynccpu-1.2.2.dist-info/LICENSE
asynccpu-1.2.2.dist-info/METADATA
asynccpu-1.2.2.dist-info/WHEEL
asynccpu-1.2.2.dist-info/top_level.txt
asynccpu-1.2.2.dist-info/RECORD
