Metadata-Version: 2.1
Name: asynccpu
Version: 1.2.2
Summary: Supports async / await pattern for CPU-bound operations.
Home-page: https://github.com/yukihiko-shinoda/asynccpu
Author: Yukihiko Shinoda
Author-email: yuk.hik.future@gmail.com
License: UNKNOWN
Keywords: asynccpu
Platform: UNKNOWN
Classifier: Development Status :: 5 - Production/Stable
Classifier: Framework :: AsyncIO
Classifier: Intended Audience :: Developers
Classifier: License :: OSI Approved :: MIT License
Classifier: Natural Language :: English
Classifier: Operating System :: OS Independent
Classifier: Programming Language :: Python
Classifier: Programming Language :: Python :: 3
Classifier: Programming Language :: Python :: 3.8
Classifier: Programming Language :: Python :: 3.9
Classifier: Topic :: Software Development :: Libraries
Classifier: Topic :: Software Development :: Libraries :: Python Modules
Classifier: Typing :: Typed
Requires-Python: >=3.8
License-File: LICENSE
Requires-Dist: psutil
